SM3/SM3.py
SM3/__init__.py
torch_SM3-0.1.0.dist-info/LICENSE
torch_SM3-0.1.0.dist-info/METADATA
torch_SM3-0.1.0.dist-info/WHEEL
torch_SM3-0.1.0.dist-info/top_level.txt
torch_SM3-0.1.0.dist-info/RECORD
