Metadata-Version: 2.1
Name: torch-SM3
Version: 0.1.0
Summary: Adds the memory efficient SM3 optimizer to PyTorch.
Home-page: https://github.com/Enealor/PyTorch-SM3
Author: Eleanor Holland
Author-email: holland.dwight@gmail.com
License: Apache-2
Platform: UNKNOWN
Classifier: Intended Audience :: Science/Research
Classifier: License :: OSI Approved :: Apache Software License
Classifier: Programming Language :: Python :: 3.7
Classifier: Programming Language :: Python :: 3.8
Classifier: Topic :: Scientific/Engineering
Classifier: Topic :: Scientific/Engineering :: Mathematics
Classifier: Topic :: Scientific/Engineering :: Artificial Intelligence
Classifier: Topic :: Software Development :: Libraries :: Python Modules
Requires-Dist: torch
